votespackage/__init__.py
votespackage/voteshandler.py
votes_package_x21127336-0.0.2.dist-info/LICENSE
votes_package_x21127336-0.0.2.dist-info/METADATA
votes_package_x21127336-0.0.2.dist-info/WHEEL
votes_package_x21127336-0.0.2.dist-info/top_level.txt
votes_package_x21127336-0.0.2.dist-info/RECORD
